eight/__init__.py
eight/utils.py
eight-1.0.1.dist-info/LICENSE
eight-1.0.1.dist-info/METADATA
eight-1.0.1.dist-info/WHEEL
eight-1.0.1.dist-info/top_level.txt
eight-1.0.1.dist-info/RECORD
