Metadata-Version: 1.1
Name: eight
Version: 1.0.1
Summary: Python 2 to the power of 3. A lightweight porting helper library.
Home-page: https://github.com/kislyuk/eight
Author: Andrey Kislyuk
Author-email: kislyuk@gmail.com
License: Apache Software License
Platform: MacOS X
Platform: Posix
Classifier: Intended Audience :: Developers
Classifier: License :: OSI Approved :: Apache Software License
Classifier: Operating System :: MacOS :: MacOS X
Classifier: Operating System :: POSIX
Classifier: Programming Language :: Python
Classifier: Programming Language :: Python :: 2.7
Classifier: Programming Language :: Python :: 3.3
Classifier: Programming Language :: Python :: 3.4
Classifier: Development Status :: 4 - Beta
Classifier: Topic :: Software Development :: Libraries :: Python Modules
